<?xml version="1.0" encoding="UTF-8"?>	<item><status>past</status><description>It's time for our June dance, back in Porter Square!&lt;br /&gt;&lt;br /&gt;Caller: The fabulous Linda Leslie (one of my favorite callers!)&lt;br /&gt;Music: The driving fiddle of Randy Miller, with Bruce Randall (trombone, whistle, coconuts), Peter Buchak (concertina, accordion, jaw harp), and Julie Vallimont (piano)&lt;br /&gt;Hear sound clips from BIDA dances at &lt;a href="http://www.myspace.com/bidadance" target="_blank"&gt;&lt;a href="http://www.myspace.com/bidadance" target="_blank"&gt;http://www.myspace.co...&lt;/a&gt;&lt;/a&gt;&lt;br /&gt;&lt;br /&gt;Contra Dance 7-10pm&lt;br /&gt;Dessert Potluck during the break, bring some tasty goodies!&lt;br /&gt;&lt;br /&gt;All are welcome, all dances taught. Bring a pair of non-street shoes for dancing.&lt;br /&gt;&lt;br /&gt;&lt;br /&gt;Public Transportation (strongly recommended)&lt;br /&gt;The Masonic Temple is a very short walk from the Porter Square T Station.&lt;br /&gt;&lt;br /&gt;Parking:&lt;br /&gt;There is some street parking nearby, with no parking permit needed on Sundays.&lt;br /&gt;Parking meters are not active on Sundays.&lt;br /&gt;If coming from out of town, parking at Alewife or Davis Square and taking the subway may be the best option.&lt;br /&gt;&lt;br /&gt;Cost: $10 (Cash Only)&lt;br /&gt;&lt;br /&gt;*This is a joint event, please RSVP with one of the groups.&lt;br /&gt;</description><maybe_rsvp_count>0</maybe_rsvp_count><waitlist_count>1</waitlist_count><updated>1244765202000</updated><rating><average>4.59999990463</average><count>5</count></rating><group><who>Friends</who><join_mode>open</join_mode><urlname>beantownandbeyond</urlname><id>553596</id><group_lat>42.3699989319</group_lat><group_lon>-71.0500030518</group_lon><name>Beantown and Beyond 25-40 Something Singles</name></group><yes_rsvp_count>8</yes_rsvp_count><created>1244035253000</created><visibility>public</visibility><name>Contra Dance - Night of Mayhem</name><id>10564658</id><headcount>5</headcount><utc_offset>-14400000</utc_offset><time>1244415600000</time><rsvp_limit>10</rsvp_limit><event_url>http://www.meetup.com/beantownandbeyond/events/10564658/</event_url><photo_url>http://photos1.meetupstatic.com/photos/event/3/e/a/global_8959002.jpeg</photo_url></item>