<?xml version="1.0" encoding="UTF-8"?>	<item><fee><label>Price</label><accepts>cash</accepts><currency>USD</currency><description>per person</description><amount>15.0</amount><required>0</required></fee><status>past</status><description>&lt;strong&gt;&lt;span style="color : #ff0000 ; font-size : medium"&gt;THIS IS NOT THE SAME VACATION YOU TOOK WITH YOUR SPOUSE...SO, SO MUCH MORE FUN!&lt;/span&gt;&lt;/strong&gt; &lt;span&gt; &lt;/span&gt; &lt;span style="font-size : medium"&gt;&lt;strong&gt;&lt;span style="color : #0000ff"&gt;COME AND LEARN ABOUT THIS GREAT TRIP...STAY AND DANCE.&lt;/span&gt;&lt;/strong&gt;&lt;/span&gt;   &lt;strong&gt;&lt;span&gt; &lt;/span&gt;&lt;span style="color : #ff0000 ; font-size : medium"&gt;START THE NEW YEAR WITH A TAN!&lt;/span&gt;&lt;/strong&gt; 
&lt;hr&gt;&lt;/hr&gt;
&lt;img src="http://img.constantcontact.com/letters/images/1101116784221/S.gif" width="1" height="5" style="max-height : 700px ; max-width : 700px ; display : block ; margin : 5px"&gt;&lt;/img&gt; &lt;img src="http://img.constantcontact.com/letters/images/1101116784221/S.gif" width="5" height="1" style="max-height : 700px ; max-width : 700px ; display : block ; margin : 5px"&gt;&lt;/img&gt; &lt;img src="http://img.constantcontact.com/letters/images/1101116784221/S.gif" width="5" height="1" style="max-height : 700px ; max-width : 700px ; display : block ; margin : 5px"&gt;&lt;/img&gt; GET AWAY! &lt;em&gt;&lt;strong&gt;"SINGLES WITH STYLE"&lt;/strong&gt;&lt;/em&gt; &lt;strong&gt;ESCAPE THE COLD VACATION&lt;/strong&gt; &lt;span style="color : #ff0000"&gt;&lt;strong&gt; &lt;/strong&gt;&lt;/span&gt; &lt;span style="color : #ff0000"&gt;&lt;strong&gt;START THE NEW YEAR OFF WITH A TAN.&lt;/strong&gt;&lt;/span&gt; &lt;span style="color : #ff0000"&gt;&lt;strong&gt; &lt;/strong&gt;&lt;/span&gt; &lt;span style="color : #0000ff"&gt;&lt;strong&gt;Your friends will be jealous.&lt;/strong&gt;&lt;/span&gt; &lt;span style="color : #0000ff"&gt;&lt;strong&gt; &lt;/strong&gt;&lt;/span&gt; &lt;em&gt;&lt;strong&gt;&lt;span&gt;People who vacation with us become life-long friends.&lt;/span&gt;&lt;/strong&gt;&lt;/em&gt; &lt;span&gt;&lt;strong&gt; &lt;/strong&gt;&lt;/span&gt; &lt;span style="color : #0000ff"&gt;&lt;strong&gt;Join your guides, Lilly and Dennis.&lt;/strong&gt;&lt;/span&gt; &lt;span style="color : #0000ff"&gt;&lt;strong&gt; &lt;/strong&gt;&lt;/span&gt; &lt;span style="color : #0000ff"&gt;&lt;strong&gt;We have TWO EXCELLENT people&lt;/strong&gt;&lt;/span&gt; &lt;span style="color : #0000ff"&gt;&lt;strong&gt;(one man &amp;amp; one woman) who are looking for&lt;/strong&gt;&lt;/span&gt; &lt;span style="color : #0000ff"&gt;&lt;strong&gt;roommates.&lt;/strong&gt;&lt;/span&gt;  &lt;br /&gt;

&lt;strong&gt;&lt;img src="https://origin.ih.constantcontact.com/fs138/1109866012635/img/508.jpg" width="589" style="max-height : 700px ; max-width : 700px ; margin : 5px"&gt;&lt;/img&gt;&lt;/strong&gt;  &lt;br /&gt;

 &lt;strong&gt;Make a decision...we only have 15 rooms at this price.&lt;/strong&gt; &lt;strong&gt;After these 15 rooms go, the price will increase.&lt;/strong&gt; &lt;strong&gt; &lt;/strong&gt; &lt;strong&gt;THIS IS A GREAT DEAL.&lt;/strong&gt; &lt;img src="https://imgssl.constantcontact.com/letters/images/1101116784221/PM_DP_TCAP600G1_Blue.png" width="600" height="81" style="max-height : 700px ; max-width : 700px ; display : block ; margin : 5px"&gt;&lt;/img&gt; &lt;img src="http://img.constantcontact.com/letters/images/1101116784221/S.gif" width="1" height="5" style="max-height : 700px ; max-width : 700px ; display : block ; margin : 5px"&gt;&lt;/img&gt; &lt;img src="http://img.constantcontact.com/letters/images/1101116784221/S.gif" width="1" height="5" style="max-height : 700px ; max-width : 700px ; display : block ; margin : 5px"&gt;&lt;/img&gt; &lt;img src="http://img.constantcontact.com/letters/images/1101116784221/S.gif" width="1" height="5" style="max-height : 700px ; max-width : 700px ; display : block ; margin : 5px"&gt;&lt;/img&gt; &lt;img src="http://img.constantcontact.com/letters/images/1101116784221/S.gif" width="1" height="5" style="max-height : 700px ; max-width : 700px ; display : block ; margin : 5px"&gt;&lt;/img&gt; &lt;img src="http://img.constantcontact.com/letters/images/1101116784221/S.gif" width="1" height="5" style="max-height : 700px ; max-width : 700px ; display : block ; margin : 5px"&gt;&lt;/img&gt; &lt;img src="http://img.constantcontact.com/letters/images/1101116784221/S.gif" width="1" height="5" style="max-height : 700px ; max-width : 700px ; display : block ; margin : 5px"&gt;&lt;/img&gt; &lt;img src="http://img.constantcontact.com/letters/images/1101116784221/S.gif" width="1" height="5" style="max-height : 700px ; max-width : 700px ; display : block ; margin : 5px"&gt;&lt;/img&gt; &lt;img src="http://img.constantcontact.com/letters/images/1101116784221/S.gif" width="1" height="5" style="max-height : 700px ; max-width : 700px ; display : block ; margin : 5px"&gt;&lt;/img&gt; &lt;img src="http://img.constantcontact.com/letters/images/1101116784221/S.gif" width="1" height="5" style="max-height : 700px ; max-width : 700px ; display : block ; margin : 5px"&gt;&lt;/img&gt; &lt;img src="http://img.constantcontact.com/letters/images/1101116784221/S.gif" width="1" height="5" style="max-height : 700px ; max-width : 700px ; display : block ; margin : 5px"&gt;&lt;/img&gt; &lt;img src="http://img.constantcontact.com/letters/images/1101116784221/S.gif" width="1" height="5" style="max-height : 700px ; max-width : 700px ; display : block ; margin : 5px"&gt;&lt;/img&gt; &lt;img src="http://img.constantcontact.com/letters/images/1101116784221/S.gif" width="1" height="5" style="max-height : 700px ; max-width : 700px ; display : block ; margin : 5px"&gt;&lt;/img&gt; &lt;img src="http://img.constantcontact.com/letters/images/1101116784221/S.gif" width="1" height="5" style="max-height : 700px ; max-width : 700px ; display : block ; margin : 5px"&gt;&lt;/img&gt; &lt;img src="http://img.constantcontact.com/letters/images/1101116784221/TRAVEL540G1_Beach_PMdestination_19.jpg" width="540" height="338" style="max-height : 700px ; max-width : 700px ; display : block ; margin : 5px"&gt;&lt;/img&gt; &lt;img src="http://img.constantcontact.com/letters/images/1101116784221/S.gif" width="5" height="1" style="max-height : 700px ; max-width : 700px ; display : block ; margin : 5px"&gt;&lt;/img&gt; Wishing for somewhere warm? &lt;img src="http://img.constantcontact.com/letters/images/1101116784221/S.gif" width="5" height="1" style="max-height : 700px ; max-width : 700px ; display : block ; margin : 5px"&gt;&lt;/img&gt; &lt;img src="https://origin.ih.constantcontact.com/fs031/1109866012635/img/374.jpg" width="537" style="max-height : 700px ; max-width : 700px ; margin : 5px"&gt;&lt;/img&gt; &lt;strong&gt;Relax on the shores of the Caribbean, on the beach at Punta Cana,&lt;/strong&gt; &lt;strong&gt;the beautiful island of the Dominican Republic&lt;/strong&gt; &lt;strong&gt;Sick and tired of shoveling and snow blowing? Well, we've got you covered with a fabulous winter getaway. Plenty of beach for you to work on your tan! Temperatures are typically in the mid-eighties in the winter, so we can guarantee you wont miss home.&lt;/strong&gt;  &lt;br /&gt;

&lt;span&gt;&lt;strong&gt;&lt;span&gt;&lt;a target="_blank" style="color : #0151ac ; text-decoration : underline"&gt;Learn more about our vacations here.&lt;/a&gt;&lt;/span&gt;&lt;/strong&gt;&lt;/span&gt; &lt;br /&gt;

 &lt;br /&gt;

&lt;p style="color : #ff0000"&gt;&lt;strong&gt;January 26 - February 2, 2013&lt;/strong&gt;&lt;/p&gt;
&lt;p style="color : #ff0000"&gt;&lt;strong&gt;Grand Paradise Bavaro Beach Resort &amp;amp; Spa&lt;/strong&gt;&lt;/p&gt;
&lt;p style="color : #ff0000"&gt;&lt;strong&gt;&lt;img src="https://origin.ih.constantcontact.com/fs031/1109866012635/img/375.jpg" width="249" height="193" style="max-height : 700px ; max-width : 700px ; margin : 5px"&gt;&lt;/img&gt;&lt;/strong&gt; &lt;img src="https://origin.ih.constantcontact.com/fs031/1109866012635/img/377.jpg" width="262" height="186" style="max-height : 700px ; max-width : 700px ; margin : 5px"&gt;&lt;/img&gt;&lt;/p&gt;
&lt;p style="color : #0000ff"&gt;&lt;strong&gt;$1359 per person/double occupancy&lt;/strong&gt;&lt;/p&gt;
&lt;p style="color : #0000ff"&gt;&lt;strong&gt;(single... $1,629 &amp;amp; triple occupancy available)&lt;/strong&gt;&lt;/p&gt;
&lt;p style="color : #ff0000"&gt;&lt;strong&gt;Includes non/stop air, transfers, hotel, taxes, &lt;span&gt;ALL FOOD &amp;amp; DRINKS.&lt;/span&gt;&lt;/strong&gt;&lt;/p&gt;
&lt;p style="color : #ff0000"&gt;&lt;strong&gt; &lt;/strong&gt;&lt;/p&gt;
&lt;p style="color : #0000ff"&gt;&lt;strong&gt;Payment due when you make your reservation&lt;/strong&gt; &lt;strong&gt;(plus $100 activity fee payable to "Singles with Style")&lt;/strong&gt;&lt;/p&gt;
&lt;p style="color : #0000ff"&gt;&lt;strong&gt; &lt;/strong&gt;&lt;/p&gt;
&lt;p style="color : #0000ff"&gt;&lt;strong&gt;For more information -Call Lilly O'Brien @ &lt;a target="_blank"&gt;781/329-5795&lt;/a&gt;... email @ &lt;a style="color : #0000ff"&gt;lob1234@aol.com&lt;/a&gt;&lt;/strong&gt;&lt;/p&gt;
&lt;p&gt; &lt;/p&gt;
&lt;img src="http://img.constantcontact.com/letters/images/1101116784221/PM_DP_DividerImage.png" width="548" height="41" style="max-height : 700px ; max-width : 700px ; display : block ; margin : 5px"&gt;&lt;/img&gt; &lt;img src="https://imgssl.constantcontact.com/letters/images/1101116784221/TRAVEL180G1_Airplane_SI0263.jpg" width="180" height="120" style="max-height : 700px ; max-width : 700px ; display : block ; margin : 5px"&gt;&lt;/img&gt; &lt;span style="color : #ff0000"&gt;&lt;strong&gt;YOU CAN'T BEAT THIS DEAL!&lt;/strong&gt;&lt;/span&gt; &lt;strong&gt;The essence of a tropical island paradise. With white sandy beaches, coconut trees everywhere, blue oceans and a broad range of activities, we have something for everyone.&lt;/strong&gt; &lt;strong&gt; &lt;/strong&gt; &lt;strong&gt;Cheaper than cruising...spend more time on the island.&lt;/strong&gt; &lt;img src="https://origin.ih.constantcontact.com/fs031/1109866012635/img/378.jpg" width="537" style="max-height : 700px ; max-width : 700px ; margin : 5px"&gt;&lt;/img&gt; 
&lt;p style="color : #ff0000"&gt;&lt;strong&gt;The Grand Paradise Bavaro Beach Resort &amp;amp; Spa features the following all inclusive services and amenities:&lt;/strong&gt;&lt;/p&gt;
&lt;span&gt; &lt;br /&gt;

&lt;/span&gt;
&lt;ul&gt;
&lt;li style="color : #0151ac"&gt;&lt;span&gt;&lt;strong&gt;24 hour all inclusive service&lt;/strong&gt;&lt;/span&gt;&lt;/li&gt;
&lt;li style="color : #ff0000"&gt;&lt;span&gt;&lt;strong&gt;3 meals daily plus snacks&lt;/strong&gt;&lt;/span&gt;&lt;/li&gt;
&lt;li style="color : #0151ac"&gt;&lt;span&gt;&lt;strong&gt;8 Restaurants (2 buffet and 6 à la carte)&lt;/strong&gt;&lt;/span&gt;&lt;/li&gt;
&lt;li style="color : #0151ac"&gt;&lt;span&gt;&lt;strong&gt;1 Food court on beach&lt;/strong&gt;&lt;/span&gt;&lt;/li&gt;
&lt;li style="color : #0151ac"&gt;&lt;span&gt;&lt;strong&gt;9 Bars&lt;/strong&gt;&lt;/span&gt;&lt;/li&gt;
&lt;li style="color : #ff0000"&gt;&lt;span&gt;&lt;strong&gt;All drinks (domestic drinks, beer, house wine with lunch &amp;amp; dinner)&lt;/strong&gt;&lt;/span&gt;&lt;/li&gt;
&lt;li style="color : #0151ac"&gt;&lt;span&gt;&lt;strong&gt;7 Pools (4 adult only pools)&lt;/strong&gt;&lt;/span&gt;&lt;/li&gt;
&lt;li style="color : #0151ac"&gt;&lt;span&gt;&lt;strong&gt;4 Jacuzzis&lt;/strong&gt;&lt;/span&gt;&lt;/li&gt;
&lt;li style="color : #0151ac"&gt;&lt;span&gt;&lt;strong&gt;Non-motorized land and water sports&lt;/strong&gt;&lt;/span&gt;&lt;/li&gt;
&lt;li style="color : #0151ac"&gt;&lt;span&gt;&lt;strong&gt;Fitness Centre&lt;/strong&gt;&lt;/span&gt;&lt;/li&gt;
&lt;li style="color : #0151ac"&gt;&lt;span&gt;&lt;strong&gt;Disco&lt;/strong&gt;&lt;/span&gt;&lt;/li&gt;
&lt;li style="color : #0151ac"&gt;&lt;span&gt;&lt;strong&gt;Casino&lt;/strong&gt;&lt;/span&gt;&lt;/li&gt;
&lt;li style="color : #0151ac"&gt;&lt;span&gt;&lt;strong&gt;Amphitheatre...live performances&lt;/strong&gt;&lt;/span&gt;&lt;/li&gt;
&lt;li style="color : #0151ac"&gt;&lt;span&gt;&lt;strong&gt;Daily activities&lt;/strong&gt;&lt;/span&gt;&lt;/li&gt;
&lt;li style="color : #0151ac"&gt;&lt;span&gt;&lt;strong&gt;Nightly entertainment&lt;/strong&gt;&lt;/span&gt;&lt;/li&gt;
&lt;/ul&gt;
&lt;img src="https://origin.ih.constantcontact.com/fs031/1109866012635/img/380.jpg" width="515" height="404" style="max-height : 700px ; max-width : 700px ; margin : 5px"&gt;&lt;/img&gt;  &lt;br /&gt;

&lt;img src="https://origin.ih.constantcontact.com/fs031/1109866012635/img/379.jpg" width="537" style="max-height : 700px ; max-width : 700px ; margin : 5px"&gt;&lt;/img&gt;  &lt;br /&gt;

 &lt;br /&gt;

&lt;p&gt;&lt;strong&gt;Our escort will have organized activities day/night for our group .......and you can enjoy the all-inclusive meals &amp;amp; amenities in addition at this hotel in paradise - the Grand Paradise Bavaro Beach Resort &amp;amp; Spa in sunny Punta Cana, Dominican Republic.&lt;/strong&gt;&lt;/p&gt;
&lt;p&gt;&lt;strong&gt; &lt;/strong&gt;&lt;/p&gt;
&lt;p&gt;&lt;strong&gt;The Grand Paradise Bavaro Beach Resort offers a variety of activities along with excellent resort facilities and amenities to enhance your vacation experience. Revel in fun games, organized activities, and a wide variety of land and water sports by day, and in the evening, enjoy exciting nightly entertainment, including live performances at the amphitheatre, dancing at the disco, or gaming at the casino. Lounge by one the several pools with a cocktail, or laze the day away on pristine Bavaro Beach!&lt;/strong&gt;&lt;/p&gt;
&lt;p&gt;&lt;strong&gt; &lt;/strong&gt;&lt;/p&gt;
&lt;p style="color : #ff0000"&gt;&lt;strong&gt;WE'VE RESERVED 15 ROOMS AT THE INCREDIBLY INEXPENSIVE PRICE...IT'S FIRST COME, FIRST SERVE.&lt;/strong&gt;&lt;/p&gt;
&lt;p&gt;&lt;strong&gt; &lt;/strong&gt;&lt;/p&gt;
&lt;p&gt;&lt;strong&gt;If you need a room mate, we'll find you one. &lt;br /&gt;

&lt;/strong&gt;&lt;/p&gt;
&lt;p&gt; &lt;/p&gt;
&lt;p style="color : #7f34a4"&gt;&lt;strong&gt;DECIDE NOW...&lt;/strong&gt;&lt;/p&gt;
&lt;p style="color : #7f34a4"&gt;&lt;strong&gt;THINK ABOUT IT TOMORROW ...&lt;/strong&gt;&lt;/p&gt;
&lt;p style="color : #7f34a4"&gt;&lt;strong&gt;COMMIT .&lt;/strong&gt;&lt;/p&gt;
&lt;p&gt;&lt;strong&gt; &lt;/strong&gt;&lt;/p&gt;
&lt;p&gt;&lt;strong&gt;&lt;span style="color : #ff0000 ; text-decoration : underline"&gt;See Dennis at a dance&lt;/span&gt; or &lt;span style="color : #ff0000 ; text-decoration : underline"&gt;mail your payment&lt;/span&gt; to:&lt;/strong&gt;&lt;/p&gt;
&lt;p&gt;&lt;strong&gt;SINGLES WITH STYLE, PO Box 1095, Lynnfield, MA 01940&lt;/strong&gt;&lt;/p&gt;
&lt;p style="color : #ff0000"&gt;&lt;strong&gt;Leave the cold weather behind &amp;amp; join us!&lt;/strong&gt;&lt;/p&gt;
&lt;img src="https://origin.ih.constantcontact.com/fs031/1109866012635/img/382.jpg" width="537" style="max-height : 700px ; max-width : 700px ; margin : 5px"&gt;&lt;/img&gt; &lt;img src="http://img.constantcontact.com/letters/images/1101116784221/S.gif" width="5" height="1" style="max-height : 700px ; max-width : 700px ; display : block ; margin : 5px"&gt;&lt;/img&gt; &lt;img src="http://img.constantcontact.com/letters/images/1101116784221/S.gif" width="1" height="5" style="max-height : 700px ; max-width : 700px ; display : block ; margin : 5px"&gt;&lt;/img&gt; &lt;img src="http://img.constantcontact.com/letters/images/1101116784221/S.gif" width="1" height="5" style="max-height : 700px ; max-width : 700px ; display : block ; margin : 5px"&gt;&lt;/img&gt; &lt;img src="http://img.constantcontact.com/letters/images/1101116784221/S.gif" width="1" height="5" style="max-height : 700px ; max-width : 700px ; display : block ; margin : 5px"&gt;&lt;/img&gt; &lt;img src="http://img.constantcontact.com/letters/images/1101116784221/S.gif" width="1" height="5" style="max-height : 700px ; max-width : 700px ; display : block ; margin : 5px"&gt;&lt;/img&gt; &lt;img src="http://img.constantcontact.com/letters/images/1101116784221/S.gif" width="1" height="5" style="max-height : 700px ; max-width : 700px ; display : block ; margin : 5px"&gt;&lt;/img&gt; &lt;img src="http://img.constantcontact.com/letters/images/1101116784221/S.gif" width="1" height="5" style="max-height : 700px ; max-width : 700px ; display : block ; margin : 5px"&gt;&lt;/img&gt; &lt;img src="http://img.constantcontact.com/letters/images/1101116784221/S.gif" width="1" height="5" style="max-height : 700px ; max-width : 700px ; display : block ; margin : 5px"&gt;&lt;/img&gt; &lt;img src="http://img.constantcontact.com/letters/images/1101116784221/S.gif" width="1" height="5" style="max-height : 700px ; max-width : 700px ; display : block ; margin : 5px"&gt;&lt;/img&gt; &lt;img src="http://img.constantcontact.com/letters/images/1101116784221/S.gif" width="1" height="5" style="max-height : 700px ; max-width : 700px ; display : block ; margin : 5px"&gt;&lt;/img&gt; &lt;img src="http://img.constantcontact.com/letters/images/1101116784221/S.gif" width="1" height="5" style="max-height : 700px ; max-width : 700px ; display : block ; margin : 5px"&gt;&lt;/img&gt; &lt;img src="http://img.constantcontact.com/letters/images/1101116784221/S.gif" width="1" height="5" style="max-height : 700px ; max-width : 700px ; display : block ; margin : 5px"&gt;&lt;/img&gt; &lt;img src="http://img.constantcontact.com/letters/images/1101116784221/S.gif" width="1" height="5" style="max-height : 700px ; max-width : 700px ; display : block ; margin : 5px"&gt;&lt;/img&gt; &lt;img src="http://img.constantcontact.com/letters/images/1101116784221/S.gif" width="1" height="5" style="max-height : 700px ; max-width : 700px ; display : block ; margin : 5px"&gt;&lt;/img&gt; &lt;img src="http://img.constantcontact.com/letters/images/1101116784221/PM_DP_BCAP600G1_Blue.png" width="600" height="81" style="max-height : 700px ; max-width : 700px ; display : block ; margin : 5px"&gt;&lt;/img&gt;  &lt;br /&gt;

  &lt;br /&gt;

&lt;strong&gt;FORWARD THIS INVITATION TO ALL YOUR SINGLE FRIENDS...THEY'LL THANK YOU.&lt;/strong&gt; &lt;img src="http://img.constantcontact.com/letters/images/1101116784221/S.gif" width="1" height="5" style="max-height : 700px ; max-width : 700px ; display : block ; margin : 5px"&gt;&lt;/img&gt; &lt;img src="http://img.constantcontact.com/letters/images/1101116784221/S.gif" width="1" height="5" style="max-height : 700px ; max-width : 700px ; display : block ; margin : 5px"&gt;&lt;/img&gt; &lt;img src="http://img.constantcontact.com/letters/images/1101116784221/PM_DP_BottomImage.png" width="680" height="138" style="max-height : 700px ; max-width : 700px ; display : block ; margin : 5px"&gt;&lt;/img&gt; &lt;img src="http://img.constantcontact.com/letters/images/1101116784221/S.gif" width="5" height="1" style="max-height : 700px ; max-width : 700px ; display : block ; margin : 5px"&gt;&lt;/img&gt; &lt;img src="http://img.constantcontact.com/letters/images/1101116784221/S.gif" width="1" height="5" style="max-height : 700px ; max-width : 700px ; display : block ; margin : 5px"&gt;&lt;/img&gt; &lt;span style="color : #000000 ; font-size : xx-small"&gt;&lt;span&gt;&lt;a target="_blank"&gt;Forward this email&lt;/a&gt;&lt;/span&gt;&lt;/span&gt; &lt;a href="http://visitor.constantcontact.com/do?p=un&amp;amp;mse=001ovWCSSzfMSDo-t8sAL113SwX3B-sZtgY1vaCJmbyl5Kqf2Y_TEQTNg%3D%3D&amp;amp;t=0011j2rlXgxtCBk5mky7GiXGA%3D%3D&amp;amp;l=001FCSs65SMrsI%3D&amp;amp;id=001b-xBWU3VMkeEFVOlehgnLmK2M_4VwOli&amp;amp;llr=85xwsujab" target="_blank"&gt;&lt;img src="http://img.constantcontact.com/letters/images/SafeUnsubscribe_Footer_Logo_New.png" style="max-height : 700px ; max-width : 700px ; margin : 5px"&gt;&lt;/img&gt;&lt;/a&gt; &lt;span&gt;&lt;a target="_blank"&gt;&lt;img src="http://img.constantcontact.com/letters/images/CC_Footer_Logo_New.png" style="max-height : 700px ; max-width : 700px ; margin : 5px"&gt;&lt;/img&gt;&lt;/a&gt;&lt;/span&gt; This email was sent to &lt;span&gt;&lt;a href="mailto:denserpone@gmail.com" target="_blank"&gt;denserpone@gmail.com&lt;/a&gt;&lt;/span&gt; by &lt;span&gt;&lt;a href="mailto:denserpone@gmail.com" target="_blank" style="color : #0000ff"&gt;denserpone@gmail.com&lt;/a&gt;&lt;/span&gt; &lt;span style="color : #bababa"&gt;|&lt;/span&gt; &lt;span&gt;&lt;a href="http://visitor.constantcontact.com/do?p=oo&amp;amp;mse=001ovWCSSzfMSDo-t8sAL113SwX3B-sZtgY1vaCJmbyl5Kqf2Y_TEQTNg%3D%3D&amp;amp;t=0011j2rlXgxtCBk5mky7GiXGA%3D%3D&amp;amp;l=001FCSs65SMrsI%3D&amp;amp;id=001b-xBWU3VMkeEFVOlehgnLmK2M_4VwOli&amp;amp;llr=85xwsujab" target="_blank" style="color : #0000ff"&gt;Update Profile/Email Address&lt;/a&gt;&lt;/span&gt; &lt;span style="color : #bababa"&gt;|&lt;/span&gt; Instant removal with &lt;span&gt;&lt;a href="http://visitor.constantcontact.com/do?p=un&amp;amp;mse=001ovWCSSzfMSDo-t8sAL113SwX3B-sZtgY1vaCJmbyl5Kqf2Y_TEQTNg%3D%3D&amp;amp;t=0011j2rlXgxtCBk5mky7GiXGA%3D%3D&amp;amp;l=001FCSs65SMrsI%3D&amp;amp;id=001b-xBWU3VMkeEFVOlehgnLmK2M_4VwOli&amp;amp;llr=85xwsujab" target="_blank" style="color : #0000ff"&gt;SafeUnsubscribe&lt;/a&gt;&lt;/span&gt;™ &lt;span style="color : #bababa"&gt;|&lt;/span&gt; &lt;span&gt;&lt;a target="_blank" style="color : #0000ff"&gt;Privacy Policy&lt;/a&gt;&lt;/span&gt;.  &lt;span style="color : #000000 ; font-size : xx-small"&gt;SINGLES WITH STYLE &lt;span style="color : #bababa"&gt;|&lt;/span&gt; 580 Salem St. &lt;span style="color : #bababa"&gt;|&lt;/span&gt; Wakefield &lt;span style="color : #bababa"&gt;|&lt;/span&gt; MA &lt;span style="color : #bababa"&gt;|&lt;/span&gt; 01880&lt;/span&gt;  </description><how_to_find_us>See Dennis at the reception desk.</how_to_find_us><event_hosts><event_hosts_item><member_name>Dennis Serpone</member_name><member_id>8281457</member_id></event_hosts_item></event_hosts><maybe_rsvp_count>0</maybe_rsvp_count><waitlist_count>0</waitlist_count><updated>1355546562000</updated><rating><average>0.0</average><count>0</count></rating><group><who>Social Networkers</who><join_mode>open</join_mode><urlname>SINGLES-WITH-STYLE</urlname><id>1311270</id><group_lat>42.5</group_lat><group_lon>-71.0699996948</group_lon><name>'SINGLES WITH STYLE' SINGLES DANCES</name></group><yes_rsvp_count>2</yes_rsvp_count><created>1355286182000</created><visibility>public</visibility><name>START THE NEW YEAR WITH A TAN!</name><id>95039882</id><headcount>0</headcount><utc_offset>-18000000</utc_offset><time>1355535000000</time><event_url>http://www.meetup.com/SINGLES-WITH-STYLE/events/95039882/</event_url></item>