<?xml version="1.0" encoding="UTF-8"?>	<item><venue><address_1>33 River St</address_1><state>CT</state><zip>06460</zip><lat>41.223043</lat><repinned>False</repinned><phone>(203) 882-1602</phone><name>Cafe Atlantique </name><city>Milford</city><id>702793</id><country>us</country><lon>-73.056994</lon></venue><status>past</status><description>&lt;p style="text-align : center"&gt;&lt;span style="color : #000080"&gt;Hi! This is just to let eveyone now that I will be playing at &lt;strong&gt;Cafe Atlantique&lt;/strong&gt; on &lt;strong&gt;Saturday, May 18th&lt;/strong&gt; from &lt;strong&gt;6:30 to 9:30 PM&lt;/strong&gt;. It is ALWAYS great to have some familiar faces in the crowd - and to make some new friends. If you could stop by - even for a little while - it would be greatly appreciated. As this is a public venue, feel free t o bring a friends, family or co-workers to enjoy the music, etc.    – the more, the merrier! &lt;/span&gt;&lt;/p&gt;
&lt;p&gt;&lt;span style="color : #000080"&gt; &lt;/span&gt;&lt;/p&gt;
&lt;p style="text-align : left"&gt;&lt;span style="color : #000080"&gt;&lt;span style="text-decoration : underline"&gt;&lt;strong&gt;ABOUT Tom Ferrara:&lt;/strong&gt;&lt;/span&gt; Tom a member of Party Express! and will be your event host. Tom performs a classic selection of acoustic folk and mellow rock that includes a varied mix of artists from James Taylor, Jim Croce and The Beatles to Green Day, Dave Matthews and Collective Soul. Tom has performed a number of happy hours, open mic nights, private parties, benefits and festivals. For more, check out Tom at: &lt;a href="http://www.facebook.com/TheCaptainRocks"&gt;http://www.facebook.com/TheCaptainRocks&lt;/a&gt;. &lt;/span&gt;&lt;/p&gt;
&lt;p style="text-align : left"&gt;&lt;span style="color : #000080"&gt;&lt;span style="text-decoration : underline"&gt;&lt;strong&gt;ABOUT Cafe Atlantique:&lt;/strong&gt;&lt;/span&gt; A European style cafe that offers a great selection of coffee, tea, paninis, salads, soups, crepes and baked goods, as well as wine and beer. Indoor and outdoor seating.  Live music, free wifi &amp;amp; weekly drink specials. You can find out more about Cafe Atlantique by visitng their Facebook page at: &lt;a href="http://www.facebook.com/pages/Cafe-Atlantique/48606855845"&gt;http://www.facebook.com/pages/Cafe-Atlantique/48606855845&lt;/a&gt;. Also, here's a link to YELP! with soem reviews, etc. &lt;a href="http://www.yelp.com/biz/cafe-atlantique-milford"&gt;http://www.yelp.com/biz/cafe-atlantique-milford&lt;/a&gt;.&lt;/span&gt;&lt;/p&gt;
&lt;p style="text-align : center"&gt;&lt;span style="color : #000080"&gt; &lt;/span&gt;&lt;/p&gt;
&lt;p style="text-align : center"&gt;&lt;strong&gt;&lt;em&gt;&lt;span style="color : #000080"&gt;Please help support live music!&lt;/span&gt;&lt;/em&gt;&lt;span style="color : #12466b"&gt; &lt;/span&gt;&lt;/strong&gt;&lt;/p&gt;</description><how_to_find_us>In the Cafe (ask Tom)</how_to_find_us><event_hosts><event_hosts_item><member_name>Tom</member_name><member_id>5815125</member_id></event_hosts_item></event_hosts><maybe_rsvp_count>0</maybe_rsvp_count><waitlist_count>0</waitlist_count><updated>1368927656000</updated><rating><average>0.0</average><count>0</count></rating><group><who>Party People</who><join_mode>approval</join_mode><urlname>Partyexpress</urlname><id>478650</id><group_lat>41.2900009155</group_lat><group_lon>-72.8600006104</group_lon><name>PartyExpress !!  Let's Get Together and have Fun!</name></group><yes_rsvp_count>2</yes_rsvp_count><created>1366559972000</created><visibility>public</visibility><name>Night of Acoustic Rock</name><id>115426152</id><headcount>0</headcount><utc_offset>-14400000</utc_offset><time>1368916200000</time><event_url>http://www.meetup.com/Partyexpress/events/115426152/</event_url></item>