<?xml version='1.0' encoding='utf-8'?>
<results><head><url>https://api.meetup.com/2/rsvps.xml?key=6b457b5342622446e4c3f214a6e3b15&amp;event_id=17100895&amp;order=event&amp;desc=false&amp;format=xml&amp;offset=0&amp;page=200&amp;fields=</url><method>RSVPs v2</method><description>Query for Event RSVPs by event</description><count>5</count><updated>Tue Apr 26 09:04:25 EDT 2011</updated><lat /><next /><id /><link>https://api.meetup.com/2/rsvps.xml</link><title>Meetup RSVPs v2</title><total_count>5</total_count><lon /></head><items><item><response>no</response><venue><address_1>292 Centre Street </address_1><state>MA</state><zip>02458</zip><lat>42.358246</lat><repinned>False</repinned><phone>617-527-7726</phone><name>Prana Restaurant</name><city>Newton Corner</city><id>1033348</id><country>us</country><lon>-71.184700</lon></venue><mtime>1303823065000</mtime><event><id>17100895</id><time>1303855200000</time><event_url>http://www.meetup.com/RawBoston/events/17100895/</event_url><name>FREE Talk @ PRANA: Judith Kravitz *Rescheduled* Please stay tuned!</name></event><group><join_mode>open</join_mode><urlname>RawBoston</urlname><id>733136</id><group_lat>42.3600006104</group_lat><group_lon>-71.0500030518</group_lon></group><created>1303823065000</created><member_photo><photo_link>http://photos4.meetupstatic.com/photos/member/1/2/8/2/member_2944738.jpeg</photo_link><highres_link>http://photos2.meetupstatic.com/photos/member/1/2/8/2/highres_2944738.jpeg</highres_link><photo_id>2944738</photo_id><thumb_link>http://photos4.meetupstatic.com/photos/member/1/2/8/2/thumb_2944738.jpeg</thumb_link></member_photo><tallies><waitlist>0</waitlist><maybe>0</maybe><no>3</no><yes>5</yes></tallies><rsvp_id>102399018</rsvp_id><member><member_id>5799645</member_id><name>Alexa</name></member><guests>0</guests></item><item><response>yes</response><venue><address_1>292 Centre Street </address_1><state>MA</state><zip>02458</zip><lat>42.358246</lat><repinned>False</repinned><phone>617-527-7726</phone><name>Prana Restaurant</name><city>Newton Corner</city><id>1033348</id><country>us</country><lon>-71.184700</lon></venue><mtime>1302221932000</mtime><event><id>17100895</id><time>1303855200000</time><event_url>http://www.meetup.com/RawBoston/events/17100895/</event_url><name>FREE Talk @ PRANA: Judith Kravitz *Rescheduled* Please stay tuned!</name></event><group><join_mode>open</join_mode><urlname>RawBoston</urlname><id>733136</id><group_lat>42.3600006104</group_lat><group_lon>-71.0500030518</group_lon></group><created>1302221932000</created><member_photo><photo_link>http://photos2.meetupstatic.com/photos/member/8/a/d/7/member_7175543.jpeg</photo_link><highres_link>http://photos2.meetupstatic.com/photos/member/8/a/d/7/highres_7175543.jpeg</highres_link><photo_id>7175543</photo_id><thumb_link>http://photos2.meetupstatic.com/photos/member/8/a/d/7/thumb_7175543.jpeg</thumb_link></member_photo><tallies><waitlist>0</waitlist><maybe>0</maybe><no>3</no><yes>5</yes></tallies><rsvp_id>101250074</rsvp_id><member><member_id>10017124</member_id><name>Alejandra Taco </name></member><guests>0</guests></item><item><response>yes</response><venue><address_1>292 Centre Street </address_1><state>MA</state><zip>02458</zip><lat>42.358246</lat><repinned>False</repinned><phone>617-527-7726</phone><name>Prana Restaurant</name><city>Newton Corner</city><id>1033348</id><country>us</country><lon>-71.184700</lon></venue><mtime>1303235351000</mtime><event><id>17100895</id><time>1303855200000</time><event_url>http://www.meetup.com/RawBoston/events/17100895/</event_url><name>FREE Talk @ PRANA: Judith Kravitz *Rescheduled* Please stay tuned!</name></event><comments>I'm enthusiastic about raw food AND about breathing deeply!</comments><group><join_mode>open</join_mode><urlname>RawBoston</urlname><id>733136</id><group_lat>42.3600006104</group_lat><group_lon>-71.0500030518</group_lon></group><created>1303235351000</created><member_photo><photo_link>http://photos3.meetupstatic.com/photos/member/8/7/a/5/member_7474725.jpeg</photo_link><highres_link>http://photos1.meetupstatic.com/photos/member/8/7/a/5/highres_7474725.jpeg</highres_link><photo_id>7474725</photo_id><thumb_link>http://photos1.meetupstatic.com/photos/member/8/7/a/5/thumb_7474725.jpeg</thumb_link></member_photo><tallies><waitlist>0</waitlist><maybe>0</maybe><no>3</no><yes>5</yes></tallies><rsvp_id>101994079</rsvp_id><member><member_id>10248155</member_id><name>Pauline Lim</name></member><guests>0</guests></item><item><response>no</response><venue><address_1>292 Centre Street </address_1><state>MA</state><zip>02458</zip><lat>42.358246</lat><repinned>False</repinned><phone>617-527-7726</phone><name>Prana Restaurant</name><city>Newton Corner</city><id>1033348</id><country>us</country><lon>-71.184700</lon></venue><mtime>1303055233000</mtime><event><id>17100895</id><time>1303855200000</time><event_url>http://www.meetup.com/RawBoston/events/17100895/</event_url><name>FREE Talk @ PRANA: Judith Kravitz *Rescheduled* Please stay tuned!</name></event><group><join_mode>open</join_mode><urlname>RawBoston</urlname><id>733136</id><group_lat>42.3600006104</group_lat><group_lon>-71.0500030518</group_lon></group><created>1303055233000</created><member_photo><photo_link>http://photos1.meetupstatic.com/photos/member/a/9/9/0/member_8323408.jpeg</photo_link><highres_link>http://photos3.meetupstatic.com/photos/member/a/9/9/0/highres_8323408.jpeg</highres_link><photo_id>8323408</photo_id><thumb_link>http://photos3.meetupstatic.com/photos/member/a/9/9/0/thumb_8323408.jpeg</thumb_link></member_photo><tallies><waitlist>0</waitlist><maybe>0</maybe><no>3</no><yes>5</yes></tallies><rsvp_id>101854886</rsvp_id><member><member_id>10979977</member_id><name>Wendy</name></member><guests>0</guests></item><item><response>yes</response><venue><address_1>292 Centre Street </address_1><state>MA</state><zip>02458</zip><lat>42.358246</lat><repinned>False</repinned><phone>617-527-7726</phone><name>Prana Restaurant</name><city>Newton Corner</city><id>1033348</id><country>us</country><lon>-71.184700</lon></venue><mtime>1301411187000</mtime><event><id>17100895</id><time>1303855200000</time><event_url>http://www.meetup.com/RawBoston/events/17100895/</event_url><name>FREE Talk @ PRANA: Judith Kravitz *Rescheduled* Please stay tuned!</name></event><group><join_mode>open</join_mode><urlname>RawBoston</urlname><id>733136</id><group_lat>42.3600006104</group_lat><group_lon>-71.0500030518</group_lon></group><created>1301411187000</created><member_photo><photo_link>http://photos4.meetupstatic.com/photos/member/4/4/e/6/member_10517638.jpeg</photo_link><highres_link>http://photos4.meetupstatic.com/photos/member/4/4/e/6/highres_10517638.jpeg</highres_link><photo_id>10517638</photo_id><thumb_link>http://photos4.meetupstatic.com/photos/member/4/4/e/6/thumb_10517638.jpeg</thumb_link></member_photo><tallies><waitlist>0</waitlist><maybe>0</maybe><no>3</no><yes>5</yes></tallies><rsvp_id>100582852</rsvp_id><member><member_id>12763494</member_id><name>Prana</name></member><guests>0</guests></item></items></results>
